file_manager/__init__.py
file_manager/cli.py
file_manager/logs/__init__.py
file_manager/logs/log_messages.py
file_manager/logs/logger_factory.py
file_manager/utils/__init__.py
file_manager/utils/config/__init__.py
file_manager/utils/config/constants.py
file_manager/utils/decorator.py
file_manager/utils/organizer.py
file_manager/utils/scanner.py
command_line_file_manager-2.1.3.dist-info/LICENSE
command_line_file_manager-2.1.3.dist-info/METADATA
command_line_file_manager-2.1.3.dist-info/WHEEL
command_line_file_manager-2.1.3.dist-info/entry_points.txt
command_line_file_manager-2.1.3.dist-info/RECORD
