Metadata-Version: 2.3
Name: command-line-file-manager
Version: 2.1.3
Summary: CLI tool for managing local file system storage
Home-page: https://github.com/kaliv0/command-line-file-manager.git
License: MIT
Keywords: file manager,cli tool,command line interface
Author: kaliv0
Author-email: kaloyan.ivanov88@gmail.com
Requires-Python: >=3.12,<4.0
Classifier: License :: OSI Approved :: MIT License
Classifier: Programming Language :: Python :: 3
Classifier: Programming Language :: Python :: 3.12
Classifier: Programming Language :: Python :: 3.13
Requires-Dist: click (>=8.1.8,<9.0.0)
Requires-Dist: pyyaml (>=6.0.2,<7.0.0)
Project-URL: Repository, https://github.com/kaliv0/command-line-file-manager.git
